pixhomology.pypy310-pp73-darwin.so
pixhomology-0.1.1.dist-info/RECORD
pixhomology-0.1.1.dist-info/LICENSE
pixhomology-0.1.1.dist-info/WHEEL
pixhomology-0.1.1.dist-info/top_level.txt
pixhomology-0.1.1.dist-info/METADATA
