Metadata-Version: 2.1
Name: pixhomology
Version: 0.1.1
Summary: PixHomology
Author: Riccardo Ceccaroni
Author-email: riccardo.ceccaroni.95@gmail.com
Requires-Python: >=3.7
License-File: LICENSE
Provides-Extra: test
Requires-Dist: pytest >=6.0 ; extra == 'test'
